{
  "volume": "歴史 ②",
  "title": "古代の世界",
  "subtitle": "古代文明 〜 三大宗教の成立",
  "topics": [
    {
      "topicId": "human-origins",
      "name": "人類の出現と進化",
      "hook": "今から約700万年前、アフリカで一人の祖先が立ち上がったんだ。二本の足で歩き始めたその瞬間から、人類の長い歩みが始まったんだよ。想像してみて、すごいよね？",
      "sections": [
        {
          "heading": "猿人から新人への進化",
          "body": "約700万年前、アフリカで**猿人**が出現したんだ。直立二足歩行を始めたことで両手が自由になって、道具を作ったり使ったりできるようになったのが大きな特徴だよ。約240万年前になると**原人**が現れて、火を使い始めたんだ。火のおかげで食物を加熱したり暖を取ったりできるようになって、北京原人やジャワ原人がその代表例として知られているよ。そして約20万年前、今の人類の直接の祖先である**新人**(ホモ・サピエンス)がアフリカで出現したんだ。「知恵のある人」という意味を持つこの新人が、やがて世界中に広がっていったんだよ。",
          "point": "猿人から原人、新人へと人類は進化していったんだよ。",
          "lead": "猿人→原人→新人の順に、人類は進化したよ。"
        },
        {
          "heading": "旧石器時代のくらし",
          "body": "打製石器を使って、狩猟・採集で食料を得ながら移動生活を送った時代を**旧石器時代**というんだ。この時代は寒冷な時期が繰り返される氷河時代にあたっていて、海面が低下して大陸と島が陸続きになったことで、人類は新しい土地へと移動できたんだよ。人々は洞穴やテント状の住まいで暮らし、獲物を追って移動を続けたんだ。フランスのラスコーやスペインのアルタミラには、動物が描かれた見事な洞窟壁画が残されているよ。狩りの成功を祈って描いたと考えられているんだ。不思議だよね。",
          "point": "旧石器時代は、打製石器を使い狩りや採集で移動して暮らした時代だよ。",
          "lead": "打製石器を使い、狩りと採集で移動して暮らしたよ。"
        },
        {
          "heading": "新石器時代と農耕の始まり",
          "body": "約1万年前になると、表面をみがいて仕上げた**磨製石器**や、食物の煮炊き・貯蔵に使われた土器が使われ始めたんだ。この時代を**新石器時代**といって、**農耕・牧畜**が始まったことで人々は食料を安定して得られるようになったんだよ。これにより、移動をやめて村をつくる定住生活が広がって、人々が集まって暮らす集落が各地に生まれたんだ。集落はやがて指導者を生み出し、国のもとへとつながっていくんだね。",
          "point": "新石器時代は、農耕や牧畜が始まって定住が広がった時代だよ。",
          "lead": "農耕や牧畜が始まり、定住生活が広がったよ。"
        }
      ],
      "terms": [
        {
          "term": "猿人",
          "reading": "えんじん",
          "desc": "約700万年前にアフリカで出現した最古の人類。直立二足歩行を始めた。"
        },
        {
          "term": "原人",
          "reading": "げんじん",
          "desc": "約240万年前に現れ、火を使うようになった人類。北京原人・ジャワ原人が代表。"
        },
        {
          "term": "新人",
          "reading": "しんじん",
          "desc": "約20万年前に出現した現在の人類の直接の祖先。ホモ・サピエンスともいう。"
        },
        {
          "term": "旧石器時代",
          "reading": "きゅうせっきじだい",
          "desc": "打製石器を使い狩猟・採集で移動生活をした時代。"
        },
        {
          "term": "打製石器",
          "reading": "だせいせっき",
          "desc": "石を打ち欠いて作った、旧石器時代の代表的な道具。"
        },
        {
          "term": "新石器時代",
          "reading": "しんせっきじだい",
          "desc": "磨製石器や土器を使い、農耕・牧畜が始まった時代。"
        },
        {
          "term": "磨製石器",
          "reading": "ませいせっき",
          "desc": "表面をみがいて作った、新石器時代の石器。"
        },
        {
          "term": "農耕・牧畜",
          "reading": "のうこう・ぼくちく",
          "desc": "新石器時代に始まった、食料を安定して得る生産方法。"
        }
      ],
      "summary": "約700万年前に猿人、約240万年前に原人、約20万年前に新人が出現して、人類は進化を重ねてきたんだ。旧石器時代は打製石器を使う狩猟・採集の移動生活だったけど、新石器時代には磨製石器や土器が使われるようになり、農耕・牧畜の開始とともに定住生活が始まったんだよ。",
      "summary30": "**猿人**から**原人**、**新人**へと人類は進化を重ねてきたんだ。**旧石器時代**は打製石器を使う狩猟・採集の移動生活だったけど、**新石器時代**には磨製石器や土器が使われるようになり、**農耕・牧畜**の開始とともに定住生活が始まったんだよ。",
      "learn": [
        "猿人・原人・新人と人類が進化してきた流れ",
        "打製石器を使い狩猟採集で移動生活をした旧石器時代のくらし",
        "磨製石器や土器を使い農耕・牧畜が始まった新石器時代のくらし"
      ],
      "image": "hist02-human-origins.webp",
      "imageCaption": "人類の出現と進化"
    },
    {
      "topicId": "ancient-civilizations",
      "name": "古代文明の誕生",
      "hook": "大きな川のほとりに人々が集まって暮らし始めると、そこから文字や都市を持つ「文明」が生まれていったんだ。知ってた？世界各地の大河文明を一緒に見てみよう。",
      "sections": [
        {
          "heading": "メソポタミア文明",
          "body": "チグリス川とユーフラテス川の流域には**メソポタミア文明**が起こったんだ。「メソポタミア」とは「川の間の土地」という意味だよ。この地では、粘土板に刻む**くさび形文字**が発明されて、商業や行政の記録に使われたんだ。また月の満ち欠けを基準にした太陰暦や、時間や角度のもとになった60進法も生み出されたんだよ。紀元前18世紀ごろには、バビロニアの王が**ハンムラビ法典**を定めたんだ。「目には目を、歯には歯を」という言葉で知られているよ。",
          "point": "メソポタミア文明はくさび形文字やハンムラビ法典で知られる文明だよ。",
          "lead": "くさび形文字やハンムラビ法典が生まれた文明だよ。"
        },
        {
          "heading": "エジプト文明",
          "body": "ナイル川流域には**エジプト文明**が発達したんだ。ナイル川は定期的に洪水を起こしていて、上流から運ばれる肥沃な土が農業を支えていたんだよ。エジプトの王である**ファラオ**は自らの墓として巨大な**ピラミッド**を築かせ、近くには人の顔とライオンの体を持つスフィンクスも建てたんだ。文字としては絵のような**象形文字**(ヒエログリフ)が使われて、洪水の時期を正確に知るために1年365日の太陽暦もつくられたんだよ。",
          "point": "エジプト文明はピラミッドや象形文字で知られる文明だよ。",
          "lead": "ナイル川流域に、ピラミッドの文明が栄えたよ。"
        },
        {
          "heading": "インダス文明とその後",
          "body": "インダス川流域には**インダス文明**が栄えて、**モヘンジョ=ダロ**やハラッパーといった、整然とした街路や排水設備を備えた計画都市が造られたんだ。しかし文明が衰えると、この地にはのちに**アーリヤ人**が侵入してきて、身分制度のもとがつくられていったんだよ。この身分制度は、のちのカースト制度へとつながっていくことになるんだね。",
          "point": "インダス文明はモヘンジョ=ダロなど計画都市で知られる文明だよ。",
          "lead": "計画都市が栄え、のちに身分制度が生まれたよ。"
        }
      ],
      "terms": [
        {
          "term": "メソポタミア文明",
          "reading": "めそぽたみあぶんめい",
          "desc": "チグリス・ユーフラテス川流域で発達した文明。くさび形文字や太陰暦が生まれた。"
        },
        {
          "term": "くさび形文字",
          "reading": "くさびがたもじ",
          "desc": "メソポタミア文明で粘土板に刻まれた文字。"
        },
        {
          "term": "ハンムラビ法典",
          "reading": "はんむらびほうてん",
          "desc": "紀元前18世紀ごろバビロニアの王が定めた、「目には目を」で知られる法律。"
        },
        {
          "term": "エジプト文明",
          "reading": "えじぷとぶんめい",
          "desc": "ナイル川流域で発達した文明。ピラミッド・象形文字が特徴。"
        },
        {
          "term": "ピラミッド",
          "reading": "ぴらみっど",
          "desc": "エジプトの王ファラオの墓として築かれた巨大な石造建造物。"
        },
        {
          "term": "象形文字",
          "reading": "しょうけいもじ",
          "desc": "エジプトで使われた絵のような文字。ヒエログリフともいう。"
        },
        {
          "term": "インダス文明",
          "reading": "いんだすぶんめい",
          "desc": "インダス川流域に栄えた文明。モヘンジョ=ダロなどの計画都市が特徴。"
        },
        {
          "term": "アーリヤ人",
          "reading": "あーりやじん",
          "desc": "インダス文明衰退後にインドへ侵入し、身分制度のもとをつくった民族。"
        }
      ],
      "summary": "大河のほとりでは、都市や文字を持つ文明が各地に発達していったんだ。メソポタミア文明はくさび形文字とハンムラビ法典、エジプト文明はピラミッドと象形文字、インダス文明はモヘンジョ=ダロの計画都市で知られていて、それぞれ独自の文化を築いていったんだよ。",
      "summary30": "大河のほとりには、都市や文字を持つ文明が発達したんだ。**メソポタミア文明**はくさび形文字と**ハンムラビ法典**、**エジプト文明**はピラミッドと象形文字、**インダス文明**はモヘンジョ=ダロの計画都市で知られているよ。",
      "learn": [
        "チグリス川・ユーフラテス川流域に栄えたメソポタミア文明の特徴",
        "ナイル川流域に栄え、ピラミッドを築いたエジプト文明の特徴",
        "インダス川流域の計画都市とアーリヤ人による身分制度の始まり"
      ],
      "image": "hist02-civ.webp",
      "imageCaption": ""
    },
    {
      "topicId": "chinese-civilization",
      "name": "中国文明の発展",
      "hook": "黄河や長江のほとりで生まれた中国文明は、やがて漢字のもとになる文字や、今も学ばれる思想家の教えを生み出していったんだよ。すごいよね？",
      "sections": [
        {
          "heading": "殷・周と甲骨文字",
          "body": "黄河や長江の流域では中国文明が発生したんだ。中国最古の王朝とされる**殷**では、亀の甲羅や牛の骨に占いの結果を記す**甲骨文字**が使われていて、これがのちの漢字のもとになったんだよ。殷を滅ぼした周もやがて支配力を弱めていって、多くの国が争う春秋戦国時代に入っていったんだ。",
          "point": "殷では、漢字のもとになった甲骨文字が使われていたよ。",
          "lead": "甲骨文字を使った殷から、春秋戦国の争乱へ進んだよ。"
        },
        {
          "heading": "孔子と儒教の誕生",
          "body": "春秋戦国時代には、多くの思想家が活躍したんだ。**孔子**は人を思いやる心である「仁」と、社会の秩序を守る「礼」を説いて、その教えは弟子たちによって**論語**にまとめられたんだよ。この孔子の教えはのちに儒教と呼ばれる思想となって、東アジア各国に大きな影響を与えていったんだ。同じころ、老子は「あるがままに自然に従って生きる」ことを説いて、のちの道教のもととなったんだよ。",
          "point": "孔子は仁と礼を説き、儒教のもとを作った思想家だよ。",
          "lead": "孔子が仁と礼を説き、儒教のもとになったよ。"
        },
        {
          "heading": "始皇帝の統一と秦・漢帝国",
          "body": "紀元前221年、**始皇帝**は中国を初めて統一して、「皇帝」の称号を初めて用いたんだ。文字や度量衡を統一する一方、北方民族の侵入を防ぐために**万里の長城**を築き、思想を統一するために書物を焼いて学者を弾圧する焚書坑儒も行ったんだよ。しかし厳しい政治への反発から秦は短期間で滅んでしまい、劉邦が建てた**漢**では儒教が国の学問となって、西方と結ぶ交易路である**シルクロード**を通じて絹などが運ばれたんだ。",
          "point": "始皇帝は中国を統一し、万里の長城を築いた王だよ。",
          "lead": "始皇帝が中国を統一し、漢が交易を広げたよ。"
        }
      ],
      "terms": [
        {
          "term": "殷",
          "reading": "いん",
          "desc": "甲骨文字が使われた、実在が確認されている中国最古の王朝。"
        },
        {
          "term": "甲骨文字",
          "reading": "こうこつもじ",
          "desc": "殷で亀の甲羅や牛の骨に刻まれた、漢字のもとになった文字。"
        },
        {
          "term": "孔子",
          "reading": "こうし",
          "desc": "「仁」と「礼」を説いた春秋時代の思想家。儒教の祖。"
        },
        {
          "term": "論語",
          "reading": "ろんご",
          "desc": "孔子の言行を弟子たちがまとめた書物。"
        },
        {
          "term": "始皇帝",
          "reading": "しこうてい",
          "desc": "紀元前221年に中国を初めて統一し、「皇帝」の称号を初めて用いた王。"
        },
        {
          "term": "万里の長城",
          "reading": "ばんりのちょうじょう",
          "desc": "始皇帝が北方民族の侵入を防ぐために築いた巨大な防壁。"
        },
        {
          "term": "漢",
          "reading": "かん",
          "desc": "秦の次に中国を統一し、儒教を国の学問とした大帝国。"
        },
        {
          "term": "シルクロード",
          "reading": "しるくろーど",
          "desc": "中国と西方を結んだ、絹などが運ばれた東西交易路。"
        }
      ],
      "summary": "黄河・長江流域に発生した中国文明では、殷の甲骨文字が漢字のもとになり、孔子が説いた仁と礼の教えは儒教へと発展していったんだ。紀元前221年に始皇帝が中国を統一して、次の漢はシルクロードを通じて西方と交易したんだよ。",
      "summary30": "黄河・長江流域に生まれた中国文明では、**殷**の**甲骨文字**が漢字のもとになったんだ。**孔子**が説いた仁と礼の教えは儒教へと発展し、紀元前221年に**始皇帝**が中国を統一したよ。次の**漢**は**シルクロード**を通じて西方と交易したんだね。",
      "learn": [
        "甲骨文字が使われ、漢字のもとになった殷の時代のようす",
        "孔子が説いた仁と礼の教え、儒教が生まれたこと",
        "始皇帝による中国統一と、漢の時代のシルクロード交易"
      ],
      "image": "hist02-chinese-civilization.webp",
      "imageCaption": "中国文明の発展"
    },
    {
      "topicId": "greece-rome",
      "name": "ギリシャ・ローマの世界",
      "hook": "地中海を舞台に、市民が政治に参加するポリスと、広大な地域を支配した大帝国が生まれたんだ。今の民主主義や法律のルーツ、一緒に探ってみよう。",
      "sections": [
        {
          "heading": "ポリスとアテネの民主政",
          "body": "古代ギリシャでは、都市を中心に独立した政治を行う**ポリス**が数多く形成されたんだ。ポリスの中心には丘の上の城塞であるアクロポリスが置かれていて、**アテネ**では成年男性の市民が民会に直接参加する**直接民主政**が行われたんだよ。一方、軍事を重視したスパルタは、少数の支配者が治める政治を行っていて、アテネとは対照的な国家だったんだ。紀元前5世紀には、これらポリスの連合軍が**ペルシャ戦争**で西アジアの大国ペルシャを撃退しているんだよ。すごいよね。",
          "point": "アテネは市民が参加する直接民主政を行ったポリスだよ。",
          "lead": "アテネは直接民主政、ペルシャ戦争にも勝利したよ。"
        },
        {
          "heading": "アレクサンドロス大王とヘレニズム文化",
          "body": "紀元前4世紀、マケドニアの**アレクサンドロス大王**はエジプトからインド北西部にまで及ぶ東方遠征を行ったんだ。この遠征によってギリシャの文化と東方(オリエント)の文化が融合して、**ヘレニズム文化**と呼ばれる新しい文化が生まれたんだよ。「ヘレニズム」とは「ギリシャ風」という意味なんだ。",
          "point": "東方遠征によって、ギリシャと東方の文化が混ざったヘレニズム文化が生まれたよ。",
          "lead": "東方遠征で、ヘレニズム文化が生まれたよ。"
        },
        {
          "heading": "ローマの共和政と帝政",
          "body": "一方ローマでは、王を置かず市民の代表が話し合う**共和政**がおよそ500年も続いたあと、皇帝が支配する**帝政**へと移っていったんだ。ローマ帝国は各地に水を運ぶ水道橋や、約5万人を収容する巨大な円形闘技場コロッセオを築いて、市民の権利を定めたローマ法を整えて広大な領土を治める基盤としたんだよ。395年に帝国は東西に分裂して、476年には西ローマ帝国が滅亡しているんだ。",
          "point": "ローマは共和政から帝政へ移り、のちに東西に分裂したよ。",
          "lead": "共和政から帝政へ移り、東西に分裂したよ。"
        }
      ],
      "terms": [
        {
          "term": "ポリス",
          "reading": "ぽりす",
          "desc": "古代ギリシャで都市を中心に形成された独立した都市国家。"
        },
        {
          "term": "アテネ",
          "reading": "あてね",
          "desc": "直接民主政が行われた、ギリシャ最大のポリス。"
        },
        {
          "term": "直接民主政",
          "reading": "ちょくせつみんしゅせい",
          "desc": "アテネで、成年男性の市民が民会に直接参加して行った政治。"
        },
        {
          "term": "ペルシャ戦争",
          "reading": "ぺるしゃせんそう",
          "desc": "紀元前5世紀、ギリシャのポリス連合軍がペルシャを撃退した戦争。"
        },
        {
          "term": "アレクサンドロス大王",
          "reading": "あれくさんどろすだいおう",
          "desc": "東方遠征を行い、ヘレニズム文化を生んだマケドニアの王。"
        },
        {
          "term": "ヘレニズム文化",
          "reading": "へれにずむぶんか",
          "desc": "ギリシャ文化と東方文化が融合して生まれた文化。"
        },
        {
          "term": "共和政",
          "reading": "きょうわせい",
          "desc": "王を置かず、市民の代表が話し合って行う古代ローマの政治。"
        },
        {
          "term": "帝政",
          "reading": "ていせい",
          "desc": "共和政のあとローマで行われた、皇帝が支配する政治。"
        }
      ],
      "summary": "ギリシャでは都市国家ポリスが数多く生まれて、アテネの直接民主政やペルシャ戦争での勝利がよく知られているよ。アレクサンドロス大王の東方遠征はヘレニズム文化を生み出し、ローマは共和政から帝政へ移りながら広大な地中海世界を支配していったんだ。",
      "summary30": "ギリシャには都市国家**ポリス**が数多く生まれ、**アテネ**の**直接民主政**やペルシャ戦争の勝利がよく知られているよ。**アレクサンドロス大王**の東方遠征は**ヘレニズム文化**を生み出し、ローマは共和政から帝政へ移りながら地中海世界を支配していったんだ。",
      "learn": [
        "アテネの直接民主政とスパルタの政治、ペルシャ戦争の勝利",
        "アレクサンドロス大王の東方遠征とヘレニズム文化の誕生",
        "ローマの共和政から帝政への移り変わりと東西分裂"
      ],
      "image": "hist02-greece.webp",
      "imageCaption": ""
    },
    {
      "topicId": "world-religions",
      "name": "世界の三大宗教",
      "hook": "世界には多くの人々が信じる宗教があるんだよ。仏教・キリスト教・イスラームという三大宗教は、それぞれどんな人がどんな教えを説いて生まれたんだろう？一緒に見ていこう。",
      "sections": [
        {
          "heading": "仏教の成立",
          "body": "紀元前5世紀頃、インドでは**シャカ**が人々を苦しみから救う教えを説いて、**仏教**を開いたんだ。仏教の教えは経典と呼ばれる聖典にまとめられて、のちにシルクロードを通じて中国へ、さらに6世紀には日本にも伝わっていって、アジアを中心に広く信仰されるようになったんだよ。",
          "point": "仏教は紀元前5世紀ごろ、シャカがインドで開いた宗教だよ。",
          "lead": "シャカが仏教を開き、経典にまとめられたよ。"
        },
        {
          "heading": "キリスト教の成立と広がり",
          "body": "1世紀のパレスチナでは、**イエス**が神の愛による救いを説いたんだ。イエスは十字架にかけられて処刑されてしまったけれど、その教えは弟子たちによって**キリスト教**としてまとめられて、聖書を聖典として信仰されるようになったんだよ。キリスト教は当初ローマ帝国から迫害を受けたけれど、信者が増え続けたことで、ついに4世紀末にはローマ帝国の国教として認められることになったんだ。",
          "point": "キリスト教はイエスの教えから生まれ、のちにローマの国教になったよ。",
          "lead": "イエスの教えが、ローマ帝国の国教になったよ。"
        },
        {
          "heading": "イスラームの成立",
          "body": "7世紀、アラビア半島では**ムハンマド**が唯一神アッラーを信じる**イスラーム**を開いたんだ。その教えは聖典である**クルアーン**(コーラン)にまとめられていて、信者であるムスリムは、メッカにあるカーバ神殿の方角に向かって1日5回の礼拝を行うことが定められているんだよ。",
          "point": "イスラームは7世紀にムハンマドが開いた一神教だよ。",
          "lead": "ムハンマドが開き、1日5回の礼拝を行うよ。"
        },
        {
          "heading": "一神教とエルサレム",
          "body": "仏教・キリスト教・イスラームを合わせて三大宗教というんだ。このうちキリスト教とイスラームは、唯一の神だけを信じる一神教の考え方を持っていて、その先駆けとなったのが、これらより古くから伝わるユダヤ教なんだよ。ユダヤ教・キリスト教・イスラームの三つの宗教にとって、**エルサレム**は共通の聖地となっているんだ。不思議でしょ？",
          "point": "エルサレムは、三つの宗教に共通する聖地なんだよ。",
          "lead": "エルサレムは、三つの宗教に共通する聖地だよ。"
        }
      ],
      "terms": [
        {
          "term": "シャカ",
          "reading": "しゃか",
          "desc": "紀元前5世紀頃、インドで仏教を開いた人物。"
        },
        {
          "term": "仏教",
          "reading": "ぶっきょう",
          "desc": "シャカの教えをもとにインドでおこった宗教。聖典は経典。"
        },
        {
          "term": "イエス",
          "reading": "いえす",
          "desc": "1世紀のパレスチナで神の愛による救いを説いた、キリスト教の開祖。"
        },
        {
          "term": "キリスト教",
          "reading": "きりすときょう",
          "desc": "イエスの教えをもとに広がった宗教。4世紀末にローマ帝国の国教となった。"
        },
        {
          "term": "ムハンマド",
          "reading": "むはんまど",
          "desc": "7世紀のアラビア半島でイスラームを開いた人物。"
        },
        {
          "term": "イスラーム",
          "reading": "いすらーむ",
          "desc": "ムハンマドが始めた一神教。聖典はクルアーン、聖地はメッカ。"
        },
        {
          "term": "クルアーン",
          "reading": "くるあーん",
          "desc": "ムハンマドへの啓示をまとめたイスラームの聖典。コーランともいう。"
        },
        {
          "term": "エルサレム",
          "reading": "えるされむ",
          "desc": "ユダヤ教・キリスト教・イスラーム共通の聖地。"
        }
      ],
      "summary": "仏教はシャカ、キリスト教はイエス、イスラームはムハンマドの教えから成立して、合わせて三大宗教と呼ばれているんだ。キリスト教とイスラームは一神教のユダヤ教を先駆けとしていて、エルサレムは三つの宗教に共通する聖地となっているんだよ。",
      "summary30": "**仏教**は**シャカ**、キリスト教はイエス、**イスラーム**は**ムハンマド**の教えから成立して、合わせて三大宗教と呼ばれているんだ。キリスト教とイスラームは一神教のユダヤ教を先駆けとしていて、**エルサレム**は三つの宗教に共通する聖地となっているんだよ。",
      "learn": [
        "シャカが開いた仏教が、インドから各地へ広まったこと",
        "イエスの教えから生まれたキリスト教が国教になった経緯",
        "ムハンマドが開いたイスラームの教えと礼拝のきまり",
        "一神教の考え方と、三つの宗教に共通する聖地エルサレム"
      ],
      "image": "hist02-religion.webp",
      "imageCaption": ""
    }
  ]
}